hannoy-0.1.0.dist-info/METADATA
hannoy-0.1.0.dist-info/WHEEL
hannoy-0.1.0.dist-info/licenses/LICENSE
hannoy/__init__.py
hannoy/__init__.pyi
hannoy/hannoy.cpython-311-aarch64-linux-gnu.so
hannoy/py.typed
hannoy-0.1.0.dist-info/RECORD
