Metadata-Version: 2.4
Name: hannoy
Version: 0.1.0
Classifier: Development Status :: 4 - Beta
Classifier: Intended Audience :: Developers
Classifier: Programming Language :: Python :: 3
License-File: LICENSE
Summary: HNSW Approximate Nearest Neighbors in Rust, based on LMDB and optimized for memory usage
Author-email: Kerollmops <clement@meilisearch.com>, Tamo <tamo@meilisearch.com>, Nate <natenethercott@gmail.com>
License-Expression: MIT
Requires-Python: >=3.9
Project-URL: Source, https://github.com/nnethercott/hannoy
